{
    "miniprogramRoot": "miniprogram/",
    "cloudfunctionRoot": "cloudfunctions/",
    "setting": {
        "urlCheck": true,
        "es6": true,
        "enhance": true,
        "postcss": true,
        "preloadBackgroundData": false,
        "minified": true,
        "newFeature": true,
        "coverView": true,
        "nodeModules": true,
        "autoAudits": false,
        "showShadowRootInWxmlPanel": true,
        "scopeDataCheck": false,
        "uglifyFileName": false,
        "checkInvalidKey": true,
        "checkSiteMap": true,
        "uploadWithSourceMap": true,
        "compileHotReLoad": false,
        "lazyloadPlaceholderEnable": false,
        "useMultiFrameRuntime": false,
        "useApiHook": false,
        "useApiHostProcess": false,
        "babelSetting": {
            "ignore": [],
            "disablePlugins": [],
            "outputPath": ""
        },
        "enableEngineNative": false,
        "useIsolateContext": true,
        "userConfirmedBundleSwitch": false,
        "packNpmManually": false,
        "packNpmRelationList": [
            {
                "packageJsonPath": "./package.json",
                "miniprogramNpmDistDir": "./miniprogram/"
            }
        ],
        "minifyWXSS": true,
        "disableUseStrict": false,
        "minifyWXML": true,
        "showES6CompileOption": false,
        "useCompilerPlugins": false
    },
    "appid": "wx3a936abe86523cb7",
    "projectname": "miniprogram-1",
    "libVersion": "2.18.0",
    "cloudfunctionTemplateRoot": "cloudfunctionTemplate",
    "condition": {
        "search": {
            "list": []
        },
        "conversation": {
            "list": []
        },
        "plugin": {
            "list": []
        },
        "game": {
            "list": []
        },
        "miniprogram": {
            "list": [
                {
                    "id": -1,
                    "name": "db guide",
                    "pathName": "pages/databaseGuide/databaseGuide"
                }
            ]
        }
    }
}